odoo/addons/pos_order_reorder/README.rst
odoo/addons/pos_order_reorder/__init__.py
odoo/addons/pos_order_reorder/__manifest__.py
odoo/addons/pos_order_reorder/i18n/es.po
odoo/addons/pos_order_reorder/i18n/fr.po
odoo/addons/pos_order_reorder/i18n/it.po
odoo/addons/pos_order_reorder/i18n/pos_order_reorder.pot
odoo/addons/pos_order_reorder/models/__init__.py
odoo/addons/pos_order_reorder/models/pos_config.py
odoo/addons/pos_order_reorder/models/res_config_settings.py
odoo/addons/pos_order_reorder/readme/CONFIGURE.rst
odoo/addons/pos_order_reorder/readme/CONTRIBUTORS.rst
odoo/addons/pos_order_reorder/readme/DESCRIPTION.rst
odoo/addons/pos_order_reorder/static/description/banner.png
odoo/addons/pos_order_reorder/static/description/icon.png
odoo/addons/pos_order_reorder/static/description/index.html
odoo/addons/pos_order_reorder/static/img/reorder_button.png
odoo/addons/pos_order_reorder/static/src/js/Screens/TicketScreen/ControlButtons/ReorderButton.esm.js
odoo/addons/pos_order_reorder/static/src/xml/Screens/TicketScreen/TicketScreen.xml
odoo/addons/pos_order_reorder/static/src/xml/Screens/TicketScreen/ControlButtons/ReorderButton.xml
odoo/addons/pos_order_reorder/views/res_config_settings_view.xml
odoo_addon_pos_order_reorder-16.0.0.1.3.dist-info/METADATA
odoo_addon_pos_order_reorder-16.0.0.1.3.dist-info/WHEEL
odoo_addon_pos_order_reorder-16.0.0.1.3.dist-info/top_level.txt
odoo_addon_pos_order_reorder-16.0.0.1.3.dist-info/RECORD
